LICENSE
MANIFEST.in
README.rst
setup.py
jonah/__init__.py
jonah/jonah.py
jonah/version.py
jonah.egg-info/PKG-INFO
jonah.egg-info/SOURCES.txt
jonah.egg-info/dependency_links.txt
jonah.egg-info/requires.txt
jonah.egg-info/top_level.txt
jonah/bin/jonah
jonah/support_files/.dockerignore
jonah/support_files/Dockerfile
jonah/support_files/jonah.ini
jonah/support_files/requirements.txt
jonah/support_files/test.sh
jonah/support_files/jonah/apt-packages.txt
jonah/support_files/jonah/finalize_build.sh
jonah/support_files/jonah/newrelic.ini
jonah/support_files/jonah/nginx.conf
jonah/support_files/jonah/spinup.sh
jonah/support_files/jonah/supervisord.conf
jonah/support_files/jonah/supervisord.conf~