Metadata-Version: 1.1
Name: jonah
Version: 1.1.1
Summary: A way to pack your Django Development, Deployment and Testing into Docker
Home-page: https://github.com/elgatosf/jonah
Author: Daniel Jilg
Author-email: daniel@breakthesystem.org
License: MIT
Keywords: docker container deployment build test
Platform: UNKNOWN
Classifier: Development Status :: 5 - Production/Stable
Classifier: Intended Audience :: Developers
Classifier: Topic :: Software Development :: Build Tools
Classifier: License :: OSI Approved :: MIT License
Classifier: Programming Language :: Python :: 2
Classifier: Programming Language :: Python :: 2.7
Classifier: Programming Language :: Python :: 3
Classifier: Programming Language :: Python :: 3.4
Classifier: Programming Language :: Python :: 3.5
